setup.py
yh_olap/__init__.py
yh_olap/csv_process.py
yh_olap/olap.py
yh_olap/web_drivers.py
yh_olap-2.0.2.dist-info/licenses/LICENSE
yh_olap-2.0.2.dist-info/METADATA
yh_olap-2.0.2.dist-info/WHEEL
yh_olap-2.0.2.dist-info/top_level.txt
yh_olap-2.0.2.dist-info/RECORD
