Metadata-Version: 2.4
Name: yh_olap
Version: 2.0.2
Summary: YH_OLAP的API
Author-email: zhang3 <675942084@qq.com>
Classifier: Programming Language :: Python :: 3
Classifier: License :: OSI Approved :: MIT License
Classifier: Operating System :: OS Independent
Requires-Python: >=3.8
License-File: LICENSE
Dynamic: license-file
